httpcheck/__init__.py
httpcheck/cli.py
httpcheck/common.py
httpcheck/file_handler.py
httpcheck/logger.py
httpcheck/notification.py
httpcheck/output_formatter.py
httpcheck/site_checker.py
httpcheck/tld_manager.py
httpcheck/validation.py
httpcheck-1.4.2.dist-info/licenses/LICENSE
httpcheck-1.4.2.dist-info/METADATA
httpcheck-1.4.2.dist-info/WHEEL
httpcheck-1.4.2.dist-info/entry_points.txt
httpcheck-1.4.2.dist-info/top_level.txt
httpcheck-1.4.2.dist-info/RECORD
