Metadata-Version: 2.4
Name: httpcheck
Version: 1.4.2
Summary: HTTP status code checker with advanced features
Author-email: Thomas Juul Dyhr <thomas@dyhr.com>
License: MIT
Project-URL: Homepage, https://github.com/docdyhr/httpcheck
Project-URL: Bug Tracker, https://github.com/docdyhr/httpcheck/issues
Project-URL: Documentation, https://github.com/docdyhr/httpcheck/blob/master/README.md
Classifier: Development Status :: 4 - Beta
Classifier: Environment :: Console
Classifier: Intended Audience :: System Administrators
Classifier: License :: OSI Approved :: MIT License
Classifier: Operating System :: OS Independent
Classifier: Programming Language :: Python :: 3
Classifier: Programming Language :: Python :: 3.9
Classifier: Programming Language :: Python :: 3.10
Classifier: Programming Language :: Python :: 3.11
Classifier: Programming Language :: Python :: 3.12
Classifier: Topic :: System :: Monitoring
Classifier: Topic :: System :: Networking :: Monitoring
Requires-Python: >=3.9
License-File: LICENSE
Requires-Dist: requests>=2.32.5
Requires-Dist: tabulate>=0.9.0
Requires-Dist: tqdm>=4.67.0
Requires-Dist: validators>=0.22.0
Provides-Extra: macos
Requires-Dist: rumps>=0.4.0; extra == "macos"
Requires-Dist: pyobjc-framework-Cocoa>=10.0; extra == "macos"
Requires-Dist: pyobjc-framework-Foundation>=10.0; extra == "macos"
Requires-Dist: pyobjc-framework-AppKit>=10.0; extra == "macos"
Requires-Dist: pyobjc-core>=10.0; extra == "macos"
Provides-Extra: dev
Requires-Dist: pytest>=7.0; extra == "dev"
Requires-Dist: pytest-mock>=3.0; extra == "dev"
Requires-Dist: pytest-cov>=4.0; extra == "dev"
Requires-Dist: pytest-benchmark>=5.0; extra == "dev"
Requires-Dist: pylint>=3.1.0; extra == "dev"
Requires-Dist: mypy>=1.0; extra == "dev"
Provides-Extra: build
Requires-Dist: py2app>=0.28; extra == "build"
Dynamic: license-file
